<?xml version="1.0" encoding="iso-8859-1" ?>
<!--
  ~ Copyright (C) Johannes Fähndrich - All Rights Reserved.
  ~ Unauthorized copying of this file, via any medium is strictly
  ~ prohibited Proprietary and confidential.
  ~ Written by Johannes Fähndrich <faehndrich@gmail.com.com>,  2011
  ~
  -->

<!DOCTYPE head SYSTEM "heads.dtd">
<?xml-stylesheet href="rogets.xsl" type="text/xsl" ?>

<head number="931" name="Sociality" origNum="#892." class="8" section="3" subSection="1" headGroup="3">
	<pos number="1" type="N.">
		<paragraph number="1" name="sociality">
			<sg number="1">
				<word number="1">sociality</word>
				<word number="2">sociability</word>
				<word number="3" paraRef="" posRef="adj.">sociableness</word>
			</sg>
			<sg number="2">
				<word number="1">social intercourse</word>
			</sg>
			<sg number="3">
				<word number="1">consociation</word>
			</sg>
			<sg number="4">
				<word number="1">intercourse</word>
				<word number="2">intercommunity</word>
			</sg>
			<sg number="5">
				<word number="1">consortship</word>
				<word number="2">companionship</word>
				<word number="3">comradeship</word>
			</sg>
			<sg number="6">
				<word number="1">clubbism</word>
			</sg>
			<sg number="7">
				<word number="1">esprit de corps</word>
			</sg>
		</paragraph>
		<paragraph number="2" name="conviviality">
			<sg number="1">
				<word number="1">conviviality</word>
			</sg>
			<sg number="2">
				<word number="1">good fellowship</word>
				<word number="2">good company</word>
			</sg>
			<sg number="3">
				<word number="1">joviality</word>
				<word number="2">jollity</word>
				<word number="3">savoir vivre</word>
				<word number="4">festivity</word>
				<word number="5">festive board</word>
				<word number="6">merrymaking</word>
			</sg>
			<sg number="4">
				<word number="1">loving cup!</word>
			</sg>
			<sg number="5">
				<word number="1">hospitality</word>
				<word number="2">heartiness</word>
			</sg>
			<sg number="6">
				<word number="1">cheer</word>
			</sg>
		</paragraph>
		<paragraph number="3" name="welcome">
			<sg number="1">
				<word number="1">welcome</word>
				<word number="2">welcomeness</word>
			</sg>
			<sg number="2">
				<word number="1">greeting</word>
			</sg>
			<sg number="3">
				<word number="1">hearty welcome</word>
				<word number="2">hearty reception</word>
				<word number="3">warm reception</word>
			</sg>
			<sg number="4">
				<word number="1" paraRef="courtesy" headRef="933">urbanity</word>
			</sg>
			<sg number="5">
				<word number="1">familiarity</word>
			</sg>
		</paragraph>
		<paragraph number="4" name="good fellow">
			<sg number="1">
				<word number="1">good fellow</word>
				<word number="2">jolly fellow</word>
			</sg>
			<sg number="2">
				<word number="1">bon enfant</word>
				<word number="2">bawcock</word>
			</sg>
		</paragraph>
		<paragraph number="5" name="social circle">
			<sg number="1">
				<word number="1">social circle</word>
				<word number="2">family circle</word>
			</sg>
			<sg number="2">
				<word number="1">circle of acquaintance</word>
				<word number="2">coterie</word>
				<word number="3">society</word>
				<word number="4">company</word>
			</sg>
		</paragraph>
		<paragraph number="6" name="social gathering">
			<sg number="1">
				<word number="1">social gathering</word>
				<word number="2">social reunion</word>
			</sg>
			<sg number="2">
				<word number="1" paraRef="assemblage" headRef="76">assembly</word>
			</sg>
			<sg number="3">
				<word number="1">barbecue</word>
				<word number="2">bee</word>
			</sg>
			<sg number="4">
				<word number="1">corn-husking</word>
				<word number="2">corn-shucking</word>
			</sg>
			<sg number="5">
				<word number="1">house raising</word>
				<word number="2">barn raising</word>
			</sg>
			<sg number="6">
				<word number="1">husking</word>
				<word number="2">husking-bee</word>
			</sg>
			<sg number="7">
				<word number="1">infare</word>
			</sg>
		</paragraph>
		<paragraph number="7" name="party">
			<sg number="1">
				<word number="1">party</word>
				<word number="2">entertainment</word>
				<word number="3">reception</word>
				<word number="4">levee</word>
				<word number="5">at</word>
				<word number="6">home</word>
				<word number="7">conversazione</word>
				<word number="8">soiree</word>
				<word number="9">matinée</word>
			</sg>
			<sg number="2">
				<word number="1">evening party</word>
				<word number="2">morning party</word>
				<word number="3">afternoon party</word>
				<word number="4">bridge party</word>
				<word number="5">garden party</word>
				<word number="6">surprise  party</word>
			</sg>
			<sg number="3">
				<word number="1">kettle</word>
				<word number="2">kettle drum</word>
			</sg>
			<sg number="4">
				<word number="1">partie carrée</word>
				<word number="2">dish of tea</word>
				<word number="3">ridotto</word>
				<word number="4">rout!</word>
			</sg>
			<sg number="5">
				<word number="1">housewarming</word>
			</sg>
			<sg number="6">
				<word number="1">ball</word>
				<word number="2">festival</word>
			</sg>
			<sg number="7">
				<word number="1">smoker</word>
				<word number="2">smoker-party</word>
			</sg>
			<sg number="8">
				<word number="1">sociable</word>
				<word number="2">stag party</word>
				<word number="3">hen party</word>
				<word number="4">tamasha!</word>
			</sg>
			<sg number="9">
				<word number="1">tea-party</word>
				<word number="2" paraRef="amusement" headRef="878">tea-fight</word>
			</sg>
			<sg number="10">
				<word number="1">"the feast of reason and the flow of soul"</word>
			</sg>
		</paragraph>
		<paragraph number="8" name="birthday party">
			<sg number="1">
				<word number="1">birthday party</word>
				<word number="2">Christmas party</word>
				<word number="3">New Year's Eve party</word>
				<word number="4">Thanksgiving Day Dinner</word>
			</sg>
			<sg number="2">
				<word number="1">bonenkai</word>
			</sg>
			<sg number="3">
				<word number="1">wedding reception</word>
			</sg>
		</paragraph>
		<paragraph number="9" name="visiting">
			<sg number="1">
				<word number="1">visiting</word>
			</sg>
			<sg number="2">
				<word number="1">round of visits</word>
			</sg>
			<sg number="3">
				<word number="1">call</word>
				<word number="2">morning call</word>
			</sg>
			<sg number="4">
				<word number="1" paraRef="conversation" headRef="614">interview</word>
			</sg>
			<sg number="5">
				<word number="1">assignation</word>
			</sg>
			<sg number="6">
				<word number="1">tryst</word>
				<word number="2">trysting place</word>
			</sg>
			<sg number="7">
				<word number="1">appointment</word>
			</sg>
		</paragraph>
		<paragraph number="10" name="club">
			<sg number="1">
				<word number="1" paraRef="association" headRef="741">club</word>
			</sg>
		</paragraph>
	</pos>
	<pos number="2" type="VB.">
		<paragraph number="1" name="be sociable">
			<sg number="1">
				<word number="1" paraRef="" posRef="adj.">be sociable</word>
			</sg>
			<sg number="2">
				<word number="1">know</word>
			</sg>
			<sg number="3">
				<word number="1" paraRef="" posRef="adj.">be acquainted</word>
			</sg>
			<sg number="4">
				<word number="1">associate with</word>
				<word number="2">sort with</word>
				<word number="3">keep company with</word>
				<word number="4">walk hand in hand with</word>
			</sg>
			<sg number="5">
				<word number="1">eat off the same trencher</word>
				<word number="2">club together</word>
				<word number="3">consort</word>
				<word number="4">bear one company</word>
				<word number="5">join</word>
			</sg>
			<sg number="6">
				<word number="1" paraRef="friendship" headRef="927">make acquaintance with</word>
			</sg>
			<sg number="7">
				<word number="1">make advances</word>
				<word number="2">fraternize</word>
				<word number="3">embrace</word>
			</sg>
		</paragraph>
		<paragraph number="2" name="be at home with">
			<sg number="1">
				<word number="1">be at home with</word>
				<word number="2">feel at home with</word>
				<word number="3">make oneself at home with</word>
			</sg>
			<sg number="2">
				<word number="1">make free with</word>
			</sg>
			<sg number="3">
				<word number="1">crack a bottle with</word>
			</sg>
			<sg number="4">
				<word number="1">receive hospitality</word>
				<word number="2">live at free quarters</word>
			</sg>
			<sg number="5">
				<word number="1">find the latchstring out</word>
			</sg>
		</paragraph>
		<paragraph number="3" name="visit">
			<sg number="1">
				<word number="1">visit</word>
				<word number="2">pay a visit</word>
			</sg>
			<sg number="2">
				<word number="1">interchange visits</word>
				<word number="2">interchange cards</word>
			</sg>
			<sg number="3">
				<word number="1">call at</word>
				<word number="2">call  upon</word>
			</sg>
			<sg number="4">
				<word number="1">leave a card</word>
			</sg>
			<sg number="5">
				<word number="1">drop in</word>
				<word number="2">look in</word>
			</sg>
			<sg number="6">
				<word number="1">look one up</word>
				<word number="2">beat up one's quarters</word>
			</sg>
		</paragraph>
		<paragraph number="4" name="entertain">
			<sg number="1">
				<word number="1">entertain</word>
			</sg>
			<sg number="2">
				<word number="1" paraRef="" posRef="n.">give a party</word>
			</sg>
			<sg number="3">
				<word number="1">be at home</word>
				<word number="2">see one's friends</word>
				<word number="3">hang out</word>
				<word number="4">keep open house</word>
				<word number="5">do the honors</word>
			</sg>
			<sg number="4">
				<word number="1">receive</word>
				<word number="2">receive with open arms</word>
			</sg>
			<sg number="5">
				<word number="1">welcome</word>
			</sg>
			<sg number="6">
				<word number="1" paraRef="" posRef="n.">give a warm reception</word>
			</sg>
		</paragraph>
	</pos>
	<pos number="3" type="ADJ.">
		<paragraph number="1" name="sociable">
			<sg number="1">
				<word number="1">sociable</word>
				<word number="2">companionable</word>
				<word number="3">clubbable</word>
				<word number="4">conversable</word>
				<word number="5">cosy</word>
				<word number="6">cosey</word>
				<word number="7">chatty,</word>
				<word number="8">conversational</word>
			</sg>
			<sg number="2">
				<word number="1">homiletical</word>
			</sg>
		</paragraph>
		<paragraph number="2" name="convivial">
			<sg number="1">
				<word number="1">convivial</word>
			</sg>
			<sg number="2">
				<word number="1">festive</word>
				<word number="2">festal</word>
			</sg>
			<sg number="3">
				<word number="1">jovial</word>
				<word number="2">jolly</word>
				<word number="3">hospitable</word>
			</sg>
			<sg number="4">
				<word number="1" new="1">phosphorylated</word>
			</sg>
		</paragraph>
		<paragraph number="3" name="welcome">
			<sg number="1">
				<word number="1">welcome</word>
				<word number="2">welcome as the roses in May</word>
			</sg>
			<sg number="2">
				<word number="1">feted</word>
				<word number="2">entertained</word>
			</sg>
		</paragraph>
		<paragraph number="4" name="free and easy">
			<sg number="1">
				<word number="1">free and easy</word>
				<word number="2">hall fellow well met</word>
				<word number="3">familiar</word>
				<word number="4">on visiting terms</word>
				<word number="5">acquainted</word>
			</sg>
		</paragraph>
		<paragraph number="5" name="social">
			<sg number="1">
				<word number="1">social</word>
				<word number="2">neighborly</word>
			</sg>
			<sg number="2">
				<word number="1">international</word>
			</sg>
			<sg number="3">
				<word number="1">gregarious</word>
			</sg>
		</paragraph>
	</pos>
	<pos number="4" type="ADV.">
		<paragraph number="1" name="en famille">
			<sg number="1">
				<word number="1">en famille</word>
				<word number="2">in the family circle</word>
			</sg>
			<sg number="2">
				<word number="1">sans fa
on</word>
				<word number="2">sans ceremonie</word>
			</sg>
			<sg number="3">
				<word number="1">arm in arm</word>
			</sg>
		</paragraph>
	</pos>
	<pos number="6" type="PHR.">
		<paragraph number="1" name="a crowd is not company">
			<sg number="1">
				<word number="1">"a crowd is not company"</word>
			</sg>
			<sg number="2">
				<word number="1">"be bright and jovial among your guests tonight"</word>
			</sg>
			<sg number="3">
				<word number="1">"his worth is warrant for his welcome"</word>
			</sg>
			<sg number="4">
				<word number="1">"let's be red with mirth"</word>
			</sg>
			<sg number="5">
				<word number="1">"welcome the coming speed the parting guest"</word>
			</sg>
		</paragraph>
	</pos>
</head>
