<?xml version="1.0" encoding="iso-8859-1" ?>
<!--
  ~ Copyright (C) Johannes Fähndrich - All Rights Reserved.
  ~ Unauthorized copying of this file, via any medium is strictly
  ~ prohibited Proprietary and confidential.
  ~ Written by Johannes Fähndrich <faehndrich@gmail.com.com>,  2011
  ~
  -->

<!DOCTYPE head SYSTEM "heads.dtd">
<?xml-stylesheet href="rogets.xsl" type="text/xsl" ?>

<head number="677" name="Goodness" origNum="#648." class="6" section="2" subSection="2" headGroup="13">
	<pos number="1" type="N.">
		<paragraph number="1" name="goodness">
			<sg number="1">
				<word number="1" paraRef="" posRef="adj.">goodness</word>
			</sg>
			<sg number="2">
				<word number="1">excellence</word>
				<word number="2">merit</word>
			</sg>
			<sg number="3">
				<word number="1" paraRef="virtue" headRef="986">virtue</word>
			</sg>
			<sg number="4">
				<word number="1">value</word>
				<word number="2">worth</word>
				<word number="3">price</word>
			</sg>
		</paragraph>
		<paragraph number="2" name="super-excellence">
			<sg number="1">
				<word number="1">super-excellence</word>
				<word number="2">supereminence</word>
			</sg>
			<sg number="2">
				<word number="1" paraRef="superiority" headRef="35">superiority</word>
			</sg>
			<sg number="3">
				<word number="1" paraRef="perfection" headRef="679">perfection</word>
			</sg>
			<sg number="4">
				<word number="1">coup de maitre</word>
			</sg>
			<sg number="5">
				<word number="1">masterpiece</word>
				<word number="2">chef d'ouvre</word>
				<word number="3">prime</word>
				<word number="4">flower</word>
				<word number="5">cream</word>
				<word number="6">elite</word>
				<word number="7">pick</word>
				<word number="8">A1</word>
				<word number="9">nonesuch</word>
				<word number="10">nonpareil</word>
				<word number="11">creme de la creme</word>
				<word number="12">flower of the flock</word>
				<word number="13">cock of the roost</word>
				<word number="14">salt of the earth</word>
			</sg>
			<sg number="6">
				<word number="1">champion</word>
			</sg>
			<sg number="7">
				<word number="1">prodigy</word>
			</sg>
		</paragraph>
		<paragraph number="3" name="tidbit">
			<sg number="1">
				<word number="1">tidbit</word>
			</sg>
			<sg number="2">
				<word number="1">gem</word>
				<word number="2">gem of the first water</word>
			</sg>
			<sg number="3">
				<word number="1">bijou</word>
				<word number="2">precious stone</word>
				<word number="3">jewel</word>
				<word number="4">pearl</word>
				<word number="5">diamond</word>
				<word number="6">ruby</word>
				<word number="7">brilliant</word>
				<word number="8">treasure</word>
				<word number="9" new="1">formalists</word>
				<word number="10" new="1">coppice</word>
				<word number="11" new="1">pomerium</word>
				<word number="12" new="1">chapbook</word>
			</sg>
			<sg number="4">
				<word number="1">good thing</word>
			</sg>
			<sg number="5">
				<word number="1">rara avis</word>
				<word number="2">one in a thousand</word>
			</sg>
		</paragraph>
		<paragraph number="4" name="beneficence">
			<sg number="1">
				<word number="1" paraRef="beneficence" headRef="946">beneficence</word>
			</sg>
			<sg number="2">
				<word number="1" paraRef="good man" headRef="990">good man</word>
			</sg>
		</paragraph>
	</pos>
	<pos number="2" type="VB.">
		<paragraph number="1" name="be beneficial">
			<sg number="1">
				<word number="1" paraRef="" posRef="adj.">be beneficial</word>
			</sg>
			<sg number="2">
				<word number="1">produce good</word>
				<word number="2" paraRef="good" headRef="647">do good</word>
			</sg>
			<sg number="3">
				<word number="1" paraRef="be useful" headRef="673">profit</word>
			</sg>
			<sg number="4">
				<word number="1">benefit</word>
			</sg>
			<sg number="5">
				<word number="1" paraRef="benefit" headRef="647">confer a benefit</word>
			</sg>
		</paragraph>
		<paragraph number="2" name="be the making of">
			<sg number="1">
				<word number="1">be the making of</word>
				<word number="2">do a world of good</word>
				<word number="3">make a man of</word>
			</sg>
		</paragraph>
		<paragraph number="3" name="produce a good effect">
			<sg number="1">
				<word number="1">produce a good effect</word>
			</sg>
			<sg number="2">
				<word number="1">do a good turn</word>
				<word number="2">confer an obligation</word>
			</sg>
			<sg number="3">
				<word number="1" paraRef="improve" headRef="687">improve</word>
			</sg>
		</paragraph>
		<paragraph number="4" name="do no harm">
			<sg number="1">
				<word number="1">do no harm</word>
				<word number="2">break no bones</word>
			</sg>
		</paragraph>
		<paragraph number="5" name="be good">
			<sg number="1">
				<word number="1" paraRef="" posRef="adj.">be good</word>
			</sg>
			<sg number="2">
				<word number="1">excel</word>
				<word number="2" paraRef="be superior" headRef="35">transcend</word>
			</sg>
			<sg number="3">
				<word number="1">bear away the bell</word>
			</sg>
		</paragraph>
		<paragraph number="6" name="stand the proof">
			<sg number="1">
				<word number="1">stand the proof</word>
				<word number="2">stand the test</word>
			</sg>
			<sg number="2">
				<word number="1">pass muster</word>
				<word number="2">pass an examination</word>
			</sg>
		</paragraph>
		<paragraph number="7" name="challenge comparison">
			<sg number="1">
				<word number="1">challenge comparison</word>
				<word number="2">vie</word>
				<word number="3">emulate</word>
				<word number="4">rival</word>
			</sg>
		</paragraph>
	</pos>
	<pos number="3" type="ADJ.">
		<paragraph number="1" name="harmless">
			<sg number="1">
				<word number="1">harmless</word>
				<word number="2">hurtless</word>
			</sg>
			<sg number="2">
				<word number="1">unobnoxious</word>
				<word number="2">innocuous</word>
				<word number="3">innocent</word>
				<word number="4">inoffensive</word>
			</sg>
		</paragraph>
		<paragraph number="2" name="beneficial">
			<sg number="1">
				<word number="1">beneficial</word>
				<word number="2">valuable</word>
				<word number="3">of value</word>
			</sg>
			<sg number="2">
				<word number="1" paraRef="useful" headRef="673">serviceable</word>
			</sg>
			<sg number="3">
				<word number="1">advantageous</word>
				<word number="2">edifying</word>
				<word number="3">profitable</word>
			</sg>
			<sg number="4">
				<word number="1" paraRef="healthful" headRef="685">salutary</word>
			</sg>
			<sg number="5">
				<word number="1" new="1">barehanded</word>
			</sg>
		</paragraph>
		<paragraph number="3" name="favorable">
			<sg number="1">
				<word number="1">favorable</word>
			</sg>
			<sg number="2">
				<word number="1" paraRef="hoping" headRef="897">propitious</word>
			</sg>
			<sg number="3">
				<word number="1">fair</word>
			</sg>
		</paragraph>
		<paragraph number="4" name="good">
			<sg number="1">
				<word number="1">good</word>
				<word number="2">good as gold</word>
			</sg>
			<sg number="2">
				<word number="1">excellent</word>
			</sg>
			<sg number="3">
				<word number="1">better</word>
			</sg>
			<sg number="4">
				<word number="1" paraRef="superior" headRef="35">superior</word>
			</sg>
			<sg number="5">
				<word number="1">above par</word>
			</sg>
			<sg number="6">
				<word number="1">nice</word>
				<word number="2">fine</word>
			</sg>
			<sg number="7">
				<word number="1" paraRef="true" headRef="518">genuine</word>
			</sg>
			<sg number="8">
				<word number="1" new="1">impressionable</word>
			</sg>
		</paragraph>
		<paragraph number="5" name="best">
			<sg number="1">
				<word number="1">best</word>
				<word number="2">choice</word>
				<word number="3">select</word>
				<word number="4">picked</word>
				<word number="5">elect</word>
				<word number="6">recherche</word>
				<word number="7">rare</word>
				<word number="8">priceless</word>
			</sg>
			<sg number="2">
				<word number="1">unparagoned</word>
				<word number="2" paraRef="supreme" headRef="35">unparalleled</word>
			</sg>
			<sg number="3">
				<word number="1" paraRef="superlatively" headRef="35">superlatively</word>
			</sg>
			<sg number="4">
				<word number="1">good</word>
			</sg>
			<sg number="5">
				<word number="1">bully*</word>
				<word number="2">crackajack*</word>
				<word number="3">giltedged</word>
			</sg>
			<sg number="6">
				<word number="1">superfine</word>
				<word number="2">superexcellent</word>
			</sg>
			<sg number="7">
				<word number="1">of the first water</word>
			</sg>
			<sg number="8">
				<word number="1">first-rate</word>
				<word number="2">first-class</word>
			</sg>
			<sg number="9">
				<word number="1">high- wrought</word>
				<word number="2">exquisite</word>
				<word number="3">very best</word>
				<word number="4">crack</word>
				<word number="5">prime</word>
				<word number="6">tiptop</word>
				<word number="7">capital</word>
				<word number="8">cardinal</word>
			</sg>
			<sg number="10">
				<word number="1" paraRef="perfect" headRef="679">standard</word>
			</sg>
			<sg number="11">
				<word number="1">inimitable</word>
			</sg>
		</paragraph>
		<paragraph number="6" name="admirable">
			<sg number="1">
				<word number="1">admirable</word>
				<word number="2">estimable</word>
			</sg>
			<sg number="2">
				<word number="1" paraRef="approve" headRef="973">praiseworthy</word>
			</sg>
			<sg number="3">
				<word number="1" paraRef="pleasing" headRef="867">pleasing</word>
			</sg>
			<sg number="4">
				<word number="1">couleur de rose</word>
				<word number="2">precious</word>
				<word number="3">of great price</word>
			</sg>
			<sg number="5">
				<word number="1" paraRef="dear" headRef="851">costly</word>
			</sg>
			<sg number="6">
				<word number="1">worth its weight in gold</word>
				<word number="2">worth a Jew's eye</word>
			</sg>
			<sg number="7">
				<word number="1">priceless</word>
				<word number="2">invaluable</word>
				<word number="3">inestimable</word>
				<word number="4">precious as the apple of the eye</word>
				<word number="5" new="1">canceled</word>
			</sg>
			<sg number="8">
				<word number="1" new="1">falsified</word>
			</sg>
		</paragraph>
		<paragraph number="7" name="tolerable">
			<sg number="1">
				<word number="1" paraRef="tolerable" headRef="680">tolerable</word>
			</sg>
			<sg number="2">
				<word number="1">up to the mark</word>
				<word number="2">unexceptionable</word>
				<word number="3">unobjectionable</word>
			</sg>
			<sg number="3">
				<word number="1">satisfactory</word>
				<word number="2">tidy</word>
			</sg>
		</paragraph>
		<paragraph number="8" name="in good condition">
			<sg number="1">
				<word number="1">in good condition</word>
				<word number="2">in fair condition</word>
			</sg>
			<sg number="2">
				<word number="1">fresh</word>
			</sg>
			<sg number="3">
				<word number="1" paraRef="perfect" headRef="679">sound</word>
			</sg>
		</paragraph>
		<paragraph number="9" name="unexceptional">
			<sg number="1">
				<word number="1" new="1">unexceptional</word>
			</sg>
		</paragraph>
		<paragraph number="10" name="bowlegged">
			<sg number="1">
				<word number="1" new="1">bowlegged</word>
			</sg>
		</paragraph>
		<paragraph number="11" name="morally">
			<sg number="1">
				<word number="1" new="1">morally</word>
			</sg>
		</paragraph>
	</pos>
	<pos number="4" type="ADV.">
		<paragraph number="1" name="beneficially">
			<sg number="1">
				<word number="1" paraRef="" posRef="adj.">beneficially</word>
			</sg>
			<sg number="2">
				<word number="1" paraRef="well" headRef="647">well</word>
			</sg>
		</paragraph>
	</pos>
	<pos number="6" type="PHR.">
		<paragraph number="1" name="Jewels five words long">
			<sg number="1">
				<word number="1">"Jewels five words long"</word>
			</sg>
			<sg number="2">
				<word number="1">"long may such goodness live!"</word>
			</sg>
			<sg number="3">
				<word number="1">"the luxury of doing good"</word>
			</sg>
		</paragraph>
	</pos>
</head>
